libsast/__init__.py
libsast/__main__.py
libsast/common.py
libsast/core_matcher/__init__.py
libsast/core_matcher/choice_matcher.py
libsast/core_matcher/helpers.py
libsast/core_matcher/matchers.py
libsast/core_matcher/pattern_matcher.py
libsast/core_sgrep/__init__.py
libsast/core_sgrep/helpers.py
libsast/core_sgrep/semantic_sgrep.py
libsast/exceptions.py
libsast/scanner.py
libsast/standards/cwe.yaml
libsast/standards/owasp_masvs.yaml
libsast/standards/owasp_mobile_top10_2016.yaml
libsast/standards/owasp_mobile_top10_2024.yaml
libsast/standards/owasp_web_top10_2017.yaml
libsast/standards.py
libsast-3.1.6.dist-info/LICENSE
libsast-3.1.6.dist-info/METADATA
libsast-3.1.6.dist-info/WHEEL
libsast-3.1.6.dist-info/entry_points.txt
libsast-3.1.6.dist-info/RECORD
