Metadata-Version: 2.1
Name: libsast
Version: 3.1.6
Summary: A generic SAST library built on top of semgrep and regex
Home-page: https://github.com/ajinabraham/libsast
License: LGPL-3.0-or-later
Keywords: libsast,SAST,Python SAST,SAST API,Regex SAST,Pattern Matcher
Author: Ajin Abraham
Author-email: ajin@opensecurity.in
Requires-Python: >=3.8,<4.0
Classifier: Development Status :: 4 - Beta
Classifier: Intended Audience :: Developers
Classifier: License :: OSI Approved :: GNU Lesser General Public License v3 or later (LGPLv3+)
Classifier: Programming Language :: Python :: 3
Classifier: Programming Language :: Python :: 3.8
Classifier: Programming Language :: Python :: 3.9
Classifier: Programming Language :: Python :: 3.10
Classifier: Programming Language :: Python :: 3.11
Classifier: Programming Language :: Python :: 3.12
Classifier: Programming Language :: Python :: 3.13
Classifier: Topic :: Security
Classifier: Topic :: Software Development :: Quality Assurance
Requires-Dist: billiard (>=4.2.1,<5.0.0)
Requires-Dist: pyyaml (>=6.0)
Requires-Dist: requests
Project-URL: Bug Tracker, https://github.com/ajinabraham/libsast/issues
Project-URL: Documentation, https://github.com/ajinabraham/libsast/blob/master/README.md
Project-URL: Repository, https://github.com/ajinabraham/libsast
